converter_letra_numero/__init__.py
converter_letra_numero/conversor.py
converter_letra_numero-0.1.0.dist-info/METADATA
converter_letra_numero-0.1.0.dist-info/WHEEL
converter_letra_numero-0.1.0.dist-info/top_level.txt
converter_letra_numero-0.1.0.dist-info/RECORD
